mylib_020/__init__.py
mylib_020-0.1.dist-info/LICENSE.txt
mylib_020-0.1.dist-info/METADATA
mylib_020-0.1.dist-info/WHEEL
mylib_020-0.1.dist-info/top_level.txt
mylib_020-0.1.dist-info/RECORD
