Metadata-Version: 2.1
Name: mylib-020
Version: 0.1
Summary: for calculating factorial
Author: Malhar
Author-email: captain200520@gmail.com
Classifier: Programming Language :: Python :: 3
Classifier: License :: OSI Approved :: MIT License
Classifier: Operating System :: OS Independent
License-File: LICENSE.txt
